igem_registry_api/__init__.py
igem_registry_api/__meta__.py
igem_registry_api/account.py
igem_registry_api/annotation.py
igem_registry_api/author.py
igem_registry_api/calls.py
igem_registry_api/category.py
igem_registry_api/client.py
igem_registry_api/collection.py
igem_registry_api/documentation.py
igem_registry_api/errors.py
igem_registry_api/license.py
igem_registry_api/organisation.py
igem_registry_api/part.py
igem_registry_api/rates.py
igem_registry_api/schemas.py
igem_registry_api/type.py
igem_registry_api/utils.py
igem_registry_api-0.1.0.dist-info/WHEEL
igem_registry_api-0.1.0.dist-info/METADATA
igem_registry_api-0.1.0.dist-info/RECORD
