Metadata-Version: 2.3
Name: igem-registry-api
Version: 0.1.0
Summary: High-level Python wrapper for the iGEM Registry REST API — typed, validated, and designed for biologists and developers.
Keywords: igem,synthetic-biology,bioinformatics,registry,pydantic,rest-api
Classifier: Programming Language :: Python :: 3
Classifier: Programming Language :: Python :: 3 :: Only
Classifier: Programming Language :: Python :: 3.12
Classifier: License :: OSI Approved :: MIT License
Classifier: Intended Audience :: Science/Research
Classifier: Topic :: Scientific/Engineering :: Bio-Informatics
Classifier: Topic :: Software Development :: Libraries :: Python Modules
Classifier: Typing :: Typed
Requires-Dist: biopython>=1.85
Requires-Dist: pydantic>=2.11.7
Requires-Dist: requests>=2.32.4
Requires-Dist: pytest>=8.0 ; extra == 'dev'
Requires-Dist: ruff>=0.6.0 ; extra == 'dev'
Requires-Dist: mypy>=1.10.0 ; extra == 'dev'
Requires-Dist: ipykernel>=6.30.1 ; extra == 'dev'
Requires-Dist: brotli>=1.1.0 ; extra == 'dev'
Requires-Dist: dotenv>=0.9.9 ; extra == 'dev'
Requires-Dist: rich>=14.1.0 ; extra == 'dev'
Requires-Dist: brotli>=1.1.0 ; extra == 'examples'
Requires-Dist: dotenv>=0.9.9 ; extra == 'examples'
Requires-Dist: rich>=14.1.0 ; extra == 'examples'
Requires-Python: >=3.12
Project-URL: Documentation, https://github.com/igem-munich/igem_registry_api#readme
Project-URL: Issues, https://github.com/igem-munich/igem_registry_api/issues
Project-URL: Repository, https://github.com/igem-munich/igem_registry_api
Provides-Extra: dev
Provides-Extra: examples
